{
  "run.ps1": {
    "DropId": "WebUiBaseDrop",
    "Multiple": false
  },

  "WebUI": {
    "package.json": {
      "NameTemplate": "package.json",
      "DropId": "WebUiBaseDrop",
      "Multiple": false
    },
    "package-lock.json": {
      "NameTemplate": "package-lock.json",
      "DropId": "WebUiBaseDrop",
      "Multiple": false
    },
    "src": {
      "api": {
        "Api.tsx": {
          "NameTemplate": "{{Params.Entity.Name | DeCapitalize}}Api.tsx",
          "DropId": "EntityDrop",
          "Multiple": true
        }
      },
      "components": {
        "Menu": {
          "GeneratedLabels.ts": {
            "DropId": "EntityList",
            "Multiple": false
          }
        },
        "Tables": {
          "Table.tsx": {
            "NameTemplate": "{{Params.Entity.Name}}Table.tsx",
            "DropId": "EntityDrop",
            "Multiple": true
          }
        },
        "Forms": {
          "EntityForm.tsx": {
            "NameTemplate": "{{Params.Entity.Name}}/{{Params.Entity.Name}}Form.tsx",
            "DropId": "EntityDrop",
            "Multiple": true,
            "Overwrite":  true 
          },
          "EntityFormData.ts": {
            "NameTemplate": "{{Params.Entity.Name}}/{{Params.Entity.Name}}FormData.ts",
            "DropId": "EntityDrop",
            "Multiple": true,
            "Overwrite": true 
          }
        },
        "Modals": {
          "EntityModal.tsx": {
            "NameTemplate": "{{Params.Entity.Name}}/{{Params.Entity.Name}}Modal.tsx",
            "DropId": "EntityDrop",
            "Multiple": true,
            "Overwrite": true 
          }
        },
        "Inputs": {
          "EntityInput.tsx": {
            "NameTemplate": "{{Params.Entity.Name}}/{{Params.Entity.Name}}Input.tsx",
            "DropId": "EntityDrop",
            "Multiple": true,
            "Overwrite": true
          },
          "EntityValues.ts": {
            "NameTemplate": "{{Params.Entity.Name}}/{{Params.Entity.Name}}Values.ts",
            "DropId": "EntityDrop",
            "Multiple": true,
            "Overwrite": true
          } 
        }
      },
      "models": {
        "Model.ts": {
          "NameTemplate": "{{Params.Entity.Name}}.ts",
          "DropId": "EntityDrop",
          "Multiple": true
        }
      },
      "routing": {
        "GeneratedRoutes.ts": {
          "DropId": "EntityList",
          "Multiple": false
        }
      },
      "screens": {
        "Entities": {
          "EntityForm.tsx": {
            "NameTemplate": "{{Params.Entity.Name}}/Form/{{Params.Entity.Name}}Form.tsx",
            "DropId": "EntityDrop",
            "Multiple": true,
            "Overwrite": true
          },
          "EntityForm.css": {
            "NameTemplate": "{{Params.Entity.Name}}/Form/{{Params.Entity.Name}}Form.css",
            "DropId": "EntityDrop",
            "Multiple": true,
            "Overwrite": true
          },
          "EntityList.tsx": {
            "NameTemplate": "{{Params.Entity.Name}}/List/{{Params.Entity.Name}}List.tsx",
            "DropId": "EntityDrop",
            "Multiple": true,
            "Overwrite": true
          },
          "EntityList.css": {
            "NameTemplate": "{{Params.Entity.Name}}/List/{{Params.Entity.Name}}List.css",
            "DropId": "EntityDrop",
            "Multiple": true,
            "Overwrite": true
          }
        }
      },
      "modules": {
        "actions.tsx": {
          "NameTemplate": "{{Params.Entity.Name | DeCapitalize}}/actions.tsx",
          "DropId": "EntityDrop",
          "Multiple": true
        },
        "actionTypes.tsx": {
          "NameTemplate": "{{Params.Entity.Name | DeCapitalize}}/actionTypes.tsx",
          "DropId": "EntityDrop",
          "Multiple": true
        },
        "reducer.tsx": {
          "NameTemplate": "{{Params.Entity.Name | DeCapitalize}}/reducer.tsx",
          "DropId": "EntityDrop",
          "Multiple": true
        },
        "index.tsx": {
            "NameTemplate": "index.tsx",
            "DropId": "EntityList",
            "Multiple": false
        },
        "snackbar": {
            "actions.ts": {
                "DropId": "EntityList",
                "Multiple": false
            },
            "actionTypes.ts": {
                "DropId": "EntityList",
                "Multiple": false
            },
            "reducer.ts": {
                "DropId": "EntityList",
                "Multiple": false
            }
        } 
      }
    }
  }
}